ragbits/agents/__init__.py
ragbits/agents/_main.py
ragbits/agents/cli.py
ragbits/agents/exceptions.py
ragbits/agents/py.typed
ragbits/agents/tool.py
ragbits/agents/types.py
ragbits/agents/a2a/__init__.py
ragbits/agents/a2a/server.py
ragbits/agents/mcp/__init__.py
ragbits/agents/mcp/server.py
ragbits/agents/mcp/utils.py
ragbits/agents/tools/__init__.py
ragbits/agents/tools/openai.py
ragbits/agents/tools/types.py
ragbits_agents-1.3.0.dist-info/METADATA
ragbits_agents-1.3.0.dist-info/WHEEL
ragbits_agents-1.3.0.dist-info/RECORD
